posthoc_ema/__init__.py
posthoc_ema/karras_ema.py
posthoc_ema/posthoc_ema.py
posthoc_ema/utils.py
posthoc_ema/vanilla_ema.py
posthoc_ema/visualization.py
pytorch_posthoc_ema-1.0.10.dist-info/LICENSE
pytorch_posthoc_ema-1.0.10.dist-info/METADATA
pytorch_posthoc_ema-1.0.10.dist-info/WHEEL
pytorch_posthoc_ema-1.0.10.dist-info/RECORD
