Metadata-Version: 2.1
Name: pytorch-posthoc-ema
Version: 1.0.10
Summary: Post-hoc EMA synthesis for PyTorch
License: MIT
Author: Phil Wang
Author-email: lucidrains@gmail.com>, Richard Löwenström <samedii@gmail.com
Requires-Python: >=3.9,<4.0
Classifier: License :: OSI Approved :: MIT License
Classifier: Programming Language :: Python :: 3
Classifier: Programming Language :: Python :: 3.9
Classifier: Programming Language :: Python :: 3.10
Classifier: Programming Language :: Python :: 3.11
Requires-Dist: eval-type-backport ; python_version < "3.10"
Requires-Dist: matplotlib
Requires-Dist: numpy
Requires-Dist: torch
